pytempus.cp36-win_amd64.pyd
pytempus-1.0.1.dist-info/DESCRIPTION.rst
pytempus-1.0.1.dist-info/METADATA
pytempus-1.0.1.dist-info/RECORD
pytempus-1.0.1.dist-info/WHEEL
pytempus-1.0.1.dist-info/metadata.json
pytempus-1.0.1.dist-info/top_level.txt
