Metadata-Version: 2.0
Name: pytempus
Version: 1.0.1
Summary: Tempus Python API
Home-page: UNKNOWN
Author: Oslandia
Author-email: infos@oslandia.com
License: LGPL
Platform: UNKNOWN
Classifier: Programming Language :: Python
Classifier: Operating System :: OS Independent
Classifier: Intended Audience :: Developers
Classifier: Topic :: System :: Software Distribution
Classifier: Topic :: Software Development :: Libraries :: Python Modules
Provides-Extra: develop
